{
  "main": {
    "id": "5acd4a3c6696af5a",
    "type": "split",
    "children": [
      {
        "id": "eeab6439f80a54c5",
        "type": "tabs",
        "children": [
          {
            "id": "5af5c6a2f87b7ec3",
            "type": "leaf",
            "state": {
              "type": "empty",
              "state": {}
            }
          }
        ]
      }
    ],
    "direction": "vertical"
  },
  "left": {
    "id": "986ad7381b4aa76c",
    "type": "split",
    "children": [
      {
        "id": "525ffc1865f10858",
        "type": "tabs",
        "children": [
          {
            "id": "8ef6c153e7a4ed38",
            "type": "leaf",
            "state": {
              "type": "file-explorer",
              "state": {
                "sortOrder": "alphabetical"
              }
            }
          },
          {
            "id": "68e022ef2943b75b",
            "type": "leaf",
            "state": {
              "type": "search",
              "state": {
                "query": "tag:#必考",
                "matchingCase": false,
                "explainSearch": false,
                "collapseAll": false,
                "extraContext": false,
                "sortOrder": "alphabetical"
              }
            }
          },
          {
            "id": "58e4b33a026fad29",
            "type": "leaf",
            "state": {
              "type": "bookmarks",
              "state": {}
            }
          },
          {
            "id": "2a658727394b251b",
            "type": "leaf",
            "state": {
              "type": "recent-files",
              "state": {}
            }
          }
        ]
      }
    ],
    "direction": "horizontal",
    "width": 200
  },
  "right": {
    "id": "e65120feb84dace3",
    "type": "split",
    "children": [
      {
        "id": "e0fa6f818c861393",
        "type": "tabs",
        "children": [
          {
            "id": "d5dd85784b1fe9ec",
            "type": "leaf",
            "state": {
              "type": "backlink",
              "state": {
                "collapseAll": false,
                "extraContext": true,
                "sortOrder": "alphabetical",
                "showSearch": false,
                "searchQuery": "",
                "backlinkCollapsed": false,
                "unlinkedCollapsed": true
              }
            }
          },
          {
            "id": "89566e4ae967dd41",
            "type": "leaf",
            "state": {
              "type": "outgoing-link",
              "state": {
                "linksCollapsed": false,
                "unlinkedCollapsed": true
              }
            }
          },
          {
            "id": "e5d9deda3bdad2bf",
            "type": "leaf",
            "state": {
              "type": "tag",
              "state": {
                "sortOrder": "frequency",
                "useHierarchy": true
              }
            }
          },
          {
            "id": "a0580e7d1cb5a5c4",
            "type": "leaf",
            "state": {
              "type": "outline",
              "state": {}
            }
          },
          {
            "id": "2c9ca742cf90c221",
            "type": "leaf",
            "state": {
              "type": "calendar",
              "state": {}
            }
          }
        ],
        "currentTab": 3
      }
    ],
    "direction": "horizontal",
    "width": 268.5
  },
  "left-ribbon": {
    "hiddenItems": {
      "switcher:打开快速切换": false,
      "graph:查看关系图谱": false,
      "canvas:新建白板": false,
      "templates:插入模板": false,
      "command-palette:打开命令面板": false,
      "markdown-importer:打开 Markdown 格式转换器": false,
      "workspaces:管理工作区布局": false,
      "daily-notes:打开/创建今天的日记": false,
      "obsidian-excalidraw-plugin:新建绘图文件": false,
      "omnisearch:Omnisearch": false,
      "audio-recorder:开始/结束录音": false,
      "obsidian-memos:Memos": false
    }
  },
  "active": "5af5c6a2f87b7ec3",
  "lastOpenFiles": [
    "99_学习情况记录/2024-04-19——星期五.md",
    "02_game theory/06_扩展性博弈.md",
    "01_Econometrics/03_多元线性回归.md",
    "98_attachment/Recording 20240418200059.webm",
    "01_Econometrics/零散知识点.md",
    "01_Econometrics/太白金星v计量.pdf",
    "02_game theory/07_子博弈不完全信息.md",
    "02_game theory/05_贝叶斯博弈.md",
    "02_game theory/第1次作业.pdf",
    "99_学习情况记录/2024-04-18——星期四.md",
    "02_game theory/04_案例（囚徒困境与纳什均衡）.md",
    "98_attachment/Pasted image 20240418083634.png",
    "98_attachment/Pasted image 20240418082946.png",
    "04_货币银行学/1_引言/02_金融体系概览.md",
    "04_货币银行学/2_金融市场/05_利率行为.md",
    "04_货币银行学/2_金融市场/04_理解利率.md",
    "05_经济思想史/02_前资本主义社会.md",
    "05_经济思想史/01_导论.md",
    "06_大创/01_目录.md",
    "98_attachment/Pasted image 20240418081825.png",
    "98_attachment/Pasted image 20240418081616.png",
    "98_attachment/Pasted image 20240418081550.png",
    "98_attachment/Pasted image 20240417210200.png",
    "98_attachment/Pasted image 20240417205745.png",
    "98_attachment/Pasted image 20240417205505.png",
    "98_attachment/Pasted image 20240417203557.png",
    "98_attachment/Pasted image 20240417202820.png",
    "01_Econometrics/00-看板-计量经济学.md",
    "02_game theory/00-看板-博弈论.md",
    "02_game theory/03_策略式博弈.md",
    "02_game theory/02_初步认识博弈.md",
    "01_Econometrics/04_模型设定.md",
    "03_public finance财政学/3_财政收入/01_财政收入总论.md",
    "02_game theory/第1次作业补充.pdf",
    "02_game theory/第2次作业.pdf",
    "99_学习情况记录/2024-04-16——星期二.md",
    "03_public finance财政学/3_财政收入/03_税收与经济效率.md",
    "03_public finance财政学/0_财政学看板.md",
    "04_货币银行学/0_货币银行学看板.md",
    "01_Econometrics/02_一元线性回归.md",
    "99_学习情况记录/2024-04-14——星期日.md",
    "Excalidraw",
    "03_public finance",
    "04_货币银行学/6_货币理论",
    "04_货币银行学/5_国际金融与货币政策",
    "04_货币银行学/4_中央银行与货币政策的实施"
  ]
}